MANIFEST.in
README.rst
setup.py
test_mm/__init__.py
test_mm/text.py
test_mm.egg-info/PKG-INFO
test_mm.egg-info/SOURCES.txt
test_mm.egg-info/dependency_links.txt
test_mm.egg-info/not-zip-safe
test_mm.egg-info/requires.txt
test_mm.egg-info/top_level.txt