Metadata-Version: 1.1
Name: test-mm
Version: 0.1.2
Summary: PyPI tutorial.
Home-page: https://mmagerl@bitbucket.org/mmagerl/packaging_tutorial.git
Author: mmagerl
Author-email: mmagerl@example.com
License: MM
Keywords: test tutorial
Platform: UNKNOWN
Classifier: Development Status :: 1 - Planning
Classifier: License :: Free For Home Use
Classifier: Programming Language :: Python :: 2.7
Classifier: Topic :: Education :: Testing
